typebuild/__init__.py
typebuild/app.py
typebuild/available_functions.py
typebuild/blueprint_code.py
typebuild/blueprint_text.py
typebuild/documents_management.py
typebuild/file_management.py
typebuild/function_calling_spec_maker.py
typebuild/function_management.py
typebuild/helpers.py
typebuild/llm_functions.py
typebuild/main.py
typebuild/menu.py
typebuild/project_management.py
typebuild/project_management_data.py
typebuild/prompts.py
typebuild/requirements_with_chat.py
typebuild/scrap.py
typebuild/session_state_management.py
typebuild/simple_auth.py
typebuild/plugins/__init__.py
typebuild/plugins/create_content_with_llms.py
typebuild/plugins/custom_llm.py
typebuild/plugins/data_widgets.py
typebuild/plugins/llm_functions.py
typebuild/plugins/llms.py
typebuild/tools/__init__.py
typebuild/tools/google_search.py
typebuild/tools/location_api.py
typebuild/tools/yt_search.py
datasmith-0.0.4.dist-info/LICENSE
datasmith-0.0.4.dist-info/METADATA
datasmith-0.0.4.dist-info/WHEEL
datasmith-0.0.4.dist-info/entry_points.txt
datasmith-0.0.4.dist-info/top_level.txt
datasmith-0.0.4.dist-info/RECORD
